{
    "/js/app.js": "/js/app.js",
    "/css/app.css": "/css/app.css",
    "/js/app.51c762234f984c47a62c.hot-update.js": "/js/app.51c762234f984c47a62c.hot-update.js",
    "/js/app.4bf571efb5c42bbfb21e.hot-update.js": "/js/app.4bf571efb5c42bbfb21e.hot-update.js",
    "/js/app.86d04cb5f2f4107418d4.hot-update.js": "/js/app.86d04cb5f2f4107418d4.hot-update.js",
    "/js/app.466c7bece403b843604c.hot-update.js": "/js/app.466c7bece403b843604c.hot-update.js",
    "/js/app.819315336fe4e5440bc3.hot-update.js": "/js/app.819315336fe4e5440bc3.hot-update.js",
    "/js/app.8e3732f23db8bb9c0fb0.hot-update.js": "/js/app.8e3732f23db8bb9c0fb0.hot-update.js",
    "/js/app.d18cae33a878c366bfcc.hot-update.js": "/js/app.d18cae33a878c366bfcc.hot-update.js",
    "/js/app.f1c95172c6375169e0e9.hot-update.js": "/js/app.f1c95172c6375169e0e9.hot-update.js",
    "/js/app.057e32aa467a4d538228.hot-update.js": "/js/app.057e32aa467a4d538228.hot-update.js",
    "/js/app.1b922bcd164b793b7dec.hot-update.js": "/js/app.1b922bcd164b793b7dec.hot-update.js",
    "/js/app.e71a468e780b51d72aa7.hot-update.js": "/js/app.e71a468e780b51d72aa7.hot-update.js",
    "/js/app.c27c80ed80697af217b9.hot-update.js": "/js/app.c27c80ed80697af217b9.hot-update.js",
    "/js/app.dde635565b81a084f152.hot-update.js": "/js/app.dde635565b81a084f152.hot-update.js",
    "/js/app.ec6923c48d7a2d754420.hot-update.js": "/js/app.ec6923c48d7a2d754420.hot-update.js",
    "/js/app.333c6f6a230a540f3178.hot-update.js": "/js/app.333c6f6a230a540f3178.hot-update.js",
    "/js/app.62be6e0c38946c921cd5.hot-update.js": "/js/app.62be6e0c38946c921cd5.hot-update.js",
    "/js/app.459bb26fee38d5cdcb1c.hot-update.js": "/js/app.459bb26fee38d5cdcb1c.hot-update.js",
    "/js/app.0605288c9d22ce9fb943.hot-update.js": "/js/app.0605288c9d22ce9fb943.hot-update.js",
    "/js/app.5af316ace8ae3e844aaf.hot-update.js": "/js/app.5af316ace8ae3e844aaf.hot-update.js",
    "/js/app.29d8a476218bb593d35a.hot-update.js": "/js/app.29d8a476218bb593d35a.hot-update.js",
    "/js/app.c5de62a8146f8e8f9f1f.hot-update.js": "/js/app.c5de62a8146f8e8f9f1f.hot-update.js",
    "/js/app.ce9158018e15b8064a5f.hot-update.js": "/js/app.ce9158018e15b8064a5f.hot-update.js"
}
